dbk12/__init__.py
dbk12/cal.py
dbk12-0.1.0.dist-info/METADATA
dbk12-0.1.0.dist-info/WHEEL
dbk12-0.1.0.dist-info/top_level.txt
dbk12-0.1.0.dist-info/RECORD
